custom_dataframe/__init__.py
custom_dataframe/frontend/build/asset-manifest.json
custom_dataframe/frontend/build/bootstrap.min.css
custom_dataframe/frontend/build/index.html
custom_dataframe/frontend/build/static/css/main.01eb6489.css
custom_dataframe/frontend/build/static/css/main.01eb6489.css.map
custom_dataframe/frontend/build/static/js/main.7cc3c47b.js
custom_dataframe/frontend/build/static/js/main.7cc3c47b.js.LICENSE.txt
custom_dataframe/frontend/build/static/js/main.7cc3c47b.js.map
streamlit_editable_dataframe-3.7.0.dist-info/METADATA
streamlit_editable_dataframe-3.7.0.dist-info/WHEEL
streamlit_editable_dataframe-3.7.0.dist-info/top_level.txt
streamlit_editable_dataframe-3.7.0.dist-info/RECORD
