Metadata-Version: 2.1
Name: streamlit-editable-dataframe
Version: 3.7.0
Home-page: 
Author: 
Author-email: 
Requires-Python: >=3.6
Requires-Dist: streamlit >=0.66
